htto/__init__.py
htto-1.0.dist-info/LICENSE
htto-1.0.dist-info/METADATA
htto-1.0.dist-info/WHEEL
htto-1.0.dist-info/top_level.txt
htto-1.0.dist-info/RECORD
