Metadata-Version: 2.1
Name: htto
Version: 1.0
Summary: simple, high performance http requests library
Home-page: https://www.github.com/xsxo/htto
Author: osmz
Classifier: Programming Language :: Python :: 3
Classifier: Operating System :: OS Independent
Classifier: License :: OSI Approved :: MIT License
License-File: LICENSE
